setup.py
delimited/__init__.py
delimited/container.py
delimited/mapping.py
delimited/path.py
delimited/sequence.py
delimited/type.py
delimited.egg-info/PKG-INFO
delimited.egg-info/SOURCES.txt
delimited.egg-info/dependency_links.txt
delimited.egg-info/requires.txt
delimited.egg-info/top_level.txt
test/test_mapping.py
test/test_path.py
test/test_sequence.py