Metadata-Version: 1.1
Name: delimited
Version: 0.0.15
Summary: Defines types that allow for accessing and modifying nested data
Home-page: https://github.com/chrisantonellis/delimited
Author: Christopher Antonellis
Author-email: christopher.antonellis@gmail.com
License: MIT License
Keywords: delimited nested
Platform: UNKNOWN
Classifier: Development Status :: 3 - Alpha
